LICENSE
README.md
setup.py
slgbuilder/__init__.py
slgbuilder/bkbuilder.py
slgbuilder/graphobject.py
slgbuilder/hpfbuilder.py
slgbuilder/mbkbuilder.py
slgbuilder/mqpbobuilder.py
slgbuilder/orbuilder.py
slgbuilder/pbkbuilder.py
slgbuilder/pqpbobuilder.py
slgbuilder/qpbobuilder.py
slgbuilder/radius_neighbor_worker.py
slgbuilder/slgbuilder.py
slgbuilder.egg-info/PKG-INFO
slgbuilder.egg-info/SOURCES.txt
slgbuilder.egg-info/dependency_links.txt
slgbuilder.egg-info/requires.txt
slgbuilder.egg-info/top_level.txt