Metadata-Version: 2.1
Name: slgbuilder
Version: 0.2.1
Summary: A Python package for building and cutting sparse layered s-t graphs.
Home-page: https://github.com/Skielex/slgbuilder
Author: Niels Jeppesen
Author-email: niejep@dtu.dk
Classifier: Development Status :: 3 - Alpha
Classifier: Environment :: Console
Classifier: Intended Audience :: Developers
Classifier: Intended Audience :: Science/Research
Classifier: License :: OSI Approved :: MIT License
Classifier: Natural Language :: English
Classifier: Operating System :: OS Independent
Classifier: Programming Language :: Python
Classifier: Topic :: Scientific/Engineering :: Image Recognition
Classifier: Topic :: Scientific/Engineering :: Artificial Intelligence
Classifier: Topic :: Scientific/Engineering :: Mathematics
License-File: LICENSE
Requires-Dist: numpy
Requires-Dist: scipy
Requires-Dist: scikit-learn
Requires-Dist: thinmaxflow
Requires-Dist: thinqpbo
